example/__init__.py
example/example.py
sdkpoc-1.1.dist-info/METADATA
sdkpoc-1.1.dist-info/WHEEL
sdkpoc-1.1.dist-info/top_level.txt
sdkpoc-1.1.dist-info/RECORD
