Metadata-Version: 2.1
Name: sdkpoc
Version: 1.1
Summary: XX trc APIs.
Home-page: https://github.com
Author: my-Tech
Author-email: support@f.in
License: UNKNOWN
Platform: UNKNOWN
Classifier: Programming Language :: Python :: 3
Classifier: License :: OSI Approved :: MIT License
Classifier: Operating System :: OS Independent
Requires-Dist: requests (==2.25.1)
Requires-Dist: tornado (==6.1)
